README.md
setup.py
HDLRTool/__init__.py
HDLRTool/pip_install.py
HDLRTool/program.py
HDLRTool/system.py
HDLRTool/web.py
HDLRTool.egg-info/PKG-INFO
HDLRTool.egg-info/SOURCES.txt
HDLRTool.egg-info/dependency_links.txt
HDLRTool.egg-info/requires.txt
HDLRTool.egg-info/top_level.txt