Metadata-Version: 2.1
Name: HDLRTool
Version: 0.1.1
Summary: 寒冬利刃的工具箱 handongliren(hdlr)'s toolbox
Home-page: https://gitee.com/handongliren
Author: hdlr
Author-email: 1079489986@qq.com
Classifier: Development Status :: 3 - Alpha
Classifier: Topic :: Software Development :: Build Tools
Classifier: Programming Language :: Python :: 3.8
Classifier: License :: OSI Approved :: MIT License
Classifier: Operating System :: OS Independent
Requires-Python: >=3
